npxarr/__init__.py
npxarr/array2Ast.py
npxarr/definedException.py
npxarr/definedTypes.py
npxarr/indexConverter.py
npxarr/utils.py
npxarr/xArray.py
np_xarr-0.1.6.dist-info/LICENSE
np_xarr-0.1.6.dist-info/METADATA
np_xarr-0.1.6.dist-info/WHEEL
np_xarr-0.1.6.dist-info/top_level.txt
np_xarr-0.1.6.dist-info/RECORD
