Metadata-Version: 2.1
Name: np-xarr
Version: 0.1.6
Summary: Perform a numpy array transformation by giving examples.
Home-page: https://github.com/jagkagd/np-xarr
Author: jagkagd
Author-email: jagkagd@gmail.com
License: UNKNOWN
Platform: UNKNOWN
Classifier: Programming Language :: Python :: 3
Classifier: License :: OSI Approved :: MIT License
Classifier: Operating System :: OS Independent
Requires-Python: >=3.5
Requires-Dist: cytoolz
Requires-Dist: numpy
